nonebot_plugin_diss_anybody/__init__.py
nonebot_plugin_diss_anybody/config.py
nonebot_plugin_diss_anybody/utils.py
nonebot_plugin_diss_anybody-1.1.1.dist-info/LICENSE
nonebot_plugin_diss_anybody-1.1.1.dist-info/METADATA
nonebot_plugin_diss_anybody-1.1.1.dist-info/WHEEL
nonebot_plugin_diss_anybody-1.1.1.dist-info/RECORD
