Metadata-Version: 2.1
Name: nonebot-plugin-diss-anybody
Version: 1.1.1
Summary: 一个在指定的用户发言时，有几率回复指定的内容的nonebot插件
License: MIT
Author: SherkeyXD
Author-email: 253294679@qq.com
Requires-Python: >=3.10,<4.0
Classifier: License :: OSI Approved :: MIT License
Classifier: Programming Language :: Python :: 3
Classifier: Programming Language :: Python :: 3.10
Classifier: Programming Language :: Python :: 3.11
Requires-Dist: nonebot-adapter-onebot (>=2.2.4,<3.0.0)
Requires-Dist: nonebot2 (>=2.1.0,<3.0.0)
Requires-Dist: tinydb (>=4.8.0,<5.0.0)
